[
  {
    " id": 5,
    "meetingDate": "09/30/2021",
    "MeetingStartTime": "07:00",
    "MeetingEndTime": "10:00",
    "meetingCreator": 1,
    "comingToMeeting": [2]
  },
  {
    " id": 6,
    "meetingDate": "09/29/2021",
    "MeetingStartTime": "07:00",
    "MeetingEndTime": "10:00",
    "meetingCreator": 2,
    "comingToMeeting": [1]
  },
  {
    " id": 7,
    "meetingDate": "09/28/2021",
    "MeetingStartTime": "07:00",
    "MeetingEndTime": "09:00",
    "meetingCreator": 1,
    "comingToMeeting": [2]
  },
  {
    " id": 8,
    "meetingDate": "09/27/2021",
    "MeetingStartTime": "13:00",
    "MeetingEndTime": "15:00",
    "meetingCreator": 1,
    "comingToMeeting": [2]
  },
  {
    " id": 9,
    "meetingDate": "09/27/2021",
    "MeetingStartTime": "07:00",
    "MeetingEndTime": "08:00",
    "meetingCreator": 1,
    "comingToMeeting": [2]
  }
]
